myotp/__init__.py
myotp/__main__.py
myotp/main.py
myotp-1.1.2.dist-info/DESCRIPTION.rst
myotp-1.1.2.dist-info/METADATA
myotp-1.1.2.dist-info/RECORD
myotp-1.1.2.dist-info/WHEEL
myotp-1.1.2.dist-info/entry_points.txt
myotp-1.1.2.dist-info/metadata.json
myotp-1.1.2.dist-info/top_level.txt
