Metadata-Version: 2.0
Name: myotp
Version: 1.1.2
Summary: Tool to generate One-Time Passwords
Home-page: https://github.com/peterpakos/otp
Author: Peter Pakos
Author-email: peter.pakos@wandisco.com
License: GPLv3
Keywords: otp one time password generator auth
Platform: UNKNOWN
Classifier: Programming Language :: Python :: 2
Classifier: Programming Language :: Python :: 2.7
Classifier: Programming Language :: Python :: 3
Classifier: Programming Language :: Python :: 3.3
Classifier: Programming Language :: Python :: 3.4
Classifier: Programming Language :: Python :: 3.5
Classifier: Programming Language :: Python :: 3.6
Classifier: License :: OSI Approved :: GNU General Public License v3 (GPLv3)
Classifier: Topic :: System :: Systems Administration :: Authentication/Directory
Requires-Dist: pyotp (>=2.2.6)
